{
    "variable": [
        {
            "id": "baseUrl",
            "key": "baseUrl",
            "type": "string",
            "name": "string",
            "value": "https:\/\/idir.test:8443"
        }
    ],
    "info": {
        "name": "API Documentation - iDir - nowoczesny katalog stron",
        "_postman_id": "49cc7325-2bb3-46c5-91b1-fba2947ca52e",
        "description": "",
        "schema": "https:\/\/schema.getpostman.com\/json\/collection\/v2.1.0\/collection.json"
    },
    "item": [
        {
            "name": "Authenticated user",
            "description": "\n> Routes:\n\n    \/routes\/vendor\/icore\/api\/user.php\n\n> Controller:\n\n    N1ebieski\\ICore\\Http\\Controllers\\Api\\Auth\\UserController",
            "item": [
                {
                    "name": "Show user",
                    "request": {
                        "url": {
                            "host": "{{baseUrl}}",
                            "path": "api\/user",
                            "query": [],
                            "raw": "{{baseUrl}}\/api\/user"
                        },
                        "method": "GET",
                        "header": [
                            {
                                "key": "Content-Type",
                                "value": "application\/json"
                            },
                            {
                                "key": "Accept",
                                "value": "application\/json"
                            }
                        ],
                        "body": null,
                        "description": "Show authenticated User resource"
                    },
                    "response": [
                        {
                            "header": [],
                            "code": 200,
                            "body": "{\"data\":{\"id\":12294,\"name\":\"Deangelo Kirlin\",\"status\":{\"value\":1,\"label\":\"active\"},\"created_at\":\"2022-02-08T15:36:07.000000Z\",\"created_at_diff\":\"1 second ago\",\"updated_at\":\"2022-02-08T15:36:07.000000Z\",\"updated_at_diff\":\"1 second ago\",\"roles\":[{\"id\":3,\"name\":\"user\",\"created_at\":\"2021-01-06T16:58:51.000000Z\",\"created_at_diff\":\"1 year 1 month ago\"}]}}",
                            "name": ""
                        }
                    ]
                }
            ]
        },
        {
            "name": "Authentication",
            "description": "\n> Routes:\n\n    \/routes\/vendor\/icore\/api\/auth.php\n\n> Controllers:\n\n    N1ebieski\\ICore\\Http\\Controllers\\Api\\Auth\\RegisterController\n    N1ebieski\\ICore\\Http\\Controllers\\Api\\Auth\\TokenController",
            "item": [
                {
                    "name": "Token",
                    "request": {
                        "url": {
                            "host": "{{baseUrl}}",
                            "path": "api\/token",
                            "query": [],
                            "raw": "{{baseUrl}}\/api\/token"
                        },
                        "method": "POST",
                        "header": [
                            {
                                "key": "Content-Type",
                                "value": "application\/json"
                            },
                            {
                                "key": "Accept",
                                "value": "application\/json"
                            }
                        ],
                        "body": {
                            "mode": "raw",
                            "raw": "{\"email\":\"kontakt@demo.idir.intelekt.net.pl\",\"password\":\"demo1234\",\"remember\":true}"
                        },
                        "description": "Create access token and (optional) refresh token.\n\n<aside class=\"notice\">Access token expires after 2 hours. Refresh token expires after 1 year.<\/aside>",
                        "auth": {
                            "type": "noauth"
                        }
                    },
                    "response": [
                        {
                            "header": [],
                            "code": 201,
                            "body": "{\n \"access_token\": \"1|LN8Gmqe6cRHQpPr5X5GW9wFXuqHVK09L8FSb7Ju9\",\n \"refresh_token\": \"2|hVHAhrgiBmSbyYjbVAC17wjwAJyKK8TQmhglBAtM\"\n}",
                            "name": "success"
                        }
                    ]
                },
                {
                    "name": "Revoke token",
                    "request": {
                        "url": {
                            "host": "{{baseUrl}}",
                            "path": "api\/revoke",
                            "query": [],
                            "raw": "{{baseUrl}}\/api\/revoke"
                        },
                        "method": "POST",
                        "header": [
                            {
                                "key": "Content-Type",
                                "value": "application\/json"
                            },
                            {
                                "key": "Accept",
                                "value": "application\/json"
                            }
                        ],
                        "body": null,
                        "description": "Revoke access token and refresh token."
                    },
                    "response": [
                        {
                            "header": [],
                            "code": 204,
                            "body": "",
                            "name": "success"
                        }
                    ]
                },
                {
                    "name": "Register",
                    "request": {
                        "url": {
                            "host": "{{baseUrl}}",
                            "path": "api\/register",
                            "query": [],
                            "raw": "{{baseUrl}}\/api\/register"
                        },
                        "method": "POST",
                        "header": [
                            {
                                "key": "Content-Type",
                                "value": "application\/json"
                            },
                            {
                                "key": "Accept",
                                "value": "application\/json"
                            }
                        ],
                        "body": {
                            "mode": "raw",
                            "raw": "{\"name\":\"N1ebieski\",\"email\":\"example@example.pl\",\"password\":\"demo1234\",\"password_confirmation\":\"demo1234\",\"privacy_agreement\":true,\"contact_agreement\":true,\"marketing_agreement\":true}"
                        },
                        "description": "Create user and send email verification notification",
                        "auth": {
                            "type": "noauth"
                        }
                    },
                    "response": [
                        {
                            "header": [],
                            "code": 200,
                            "body": "{\"data\":{\"id\":12297,\"name\":\"Mr. Zander Yost\",\"status\":{\"value\":1,\"label\":\"active\"},\"created_at\":\"2022-02-08T15:36:08.000000Z\",\"created_at_diff\":\"1 second ago\",\"updated_at\":\"2022-02-08T15:36:08.000000Z\",\"updated_at_diff\":\"1 second ago\",\"roles\":[{\"id\":3,\"name\":\"user\",\"created_at\":\"2021-01-06T16:58:51.000000Z\",\"created_at_diff\":\"1 year 1 month ago\"}]}}",
                            "name": ""
                        }
                    ]
                },
                {
                    "name": "Refresh token",
                    "request": {
                        "url": {
                            "host": "{{baseUrl}}",
                            "path": "api\/refresh",
                            "query": [],
                            "raw": "{{baseUrl}}\/api\/refresh"
                        },
                        "method": "POST",
                        "header": [
                            {
                                "key": "Content-Type",
                                "value": "application\/json"
                            },
                            {
                                "key": "Accept",
                                "value": "application\/json"
                            }
                        ],
                        "body": null,
                        "description": "Create new access token and refresh token.\n\n<aside class=\"success\">Refresh token must be in the Authorization header with the value \"Bearer {YOUR_REFRESH_TOKEN}\".<\/aside>"
                    },
                    "response": [
                        {
                            "header": [],
                            "code": 201,
                            "body": "{\n \"access_token\": \"3|LN8Gmqe6cRHQpPr5X5GW9wFXuqHVK09L8FSb7Ju9\",\n \"refresh_token\": \"4|hVHAhrgiBmSbyYjbVAC17wjwAJyKK8TQmhglBAtM\"\n}",
                            "name": "success"
                        }
                    ]
                }
            ]
        },
        {
            "name": "Categories",
            "description": "\n> Routes:\n\n    \/routes\/vendor\/icore\/api\/categories.php\n    \/routes\/vendor\/idir\/api\/categories.php\n\n> Controllers:\n\n    N1ebieski\\ICore\\Http\\Controllers\\Api\\Category\\CategoryController\n    N1ebieski\\ICore\\Http\\Controllers\\Api\\Category\\Post\\CategoryController\n    N1ebieski\\IDir\\Http\\Controllers\\Api\\Category\\Dir\\CategoryController\n\n> Resource:\n\n    N1ebieski\\ICore\\Http\\Resources\\Category\\CategoryResource\n\nPermissions:\n\n- api.* - access to all api endpoints\n- api.categories.* - access to all categories endpoints\n- api.categories.view - access to endpoints with collection of categories",
            "item": [
                {
                    "name": "Index of dir's categories",
                    "request": {
                        "url": {
                            "host": "{{baseUrl}}",
                            "path": "api\/categories\/dir\/index",
                            "query": [],
                            "raw": "{{baseUrl}}\/api\/categories\/dir\/index"
                        },
                        "method": "POST",
                        "header": [
                            {
                                "key": "Content-Type",
                                "value": "application\/json"
                            },
                            {
                                "key": "Accept",
                                "value": "application\/json"
                            }
                        ],
                        "body": {
                            "mode": "raw",
                            "raw": "{\"page\":1,\"filter\":{\"except\":[20],\"search\":\"\",\"status\":1,\"parent\":0,\"orderby\":\"\",\"paginate\":50}}"
                        },
                        "description": "",
                        "auth": {
                            "type": "noauth"
                        }
                    },
                    "response": [
                        {
                            "header": [],
                            "code": 200,
                            "body": "{\"data\":[{\"id\":2571,\"name\":\"omnis ullam\",\"slug\":\"omnis-ullam\",\"icon\":null,\"status\":{\"value\":1,\"label\":\"active\"},\"real_depth\":0,\"created_at\":\"2022-02-08T15:36:06.000000Z\",\"created_at_diff\":\"1 second ago\",\"updated_at\":\"2022-02-08T15:36:06.000000Z\",\"updated_at_diff\":\"1 second ago\"},{\"id\":2572,\"name\":\"modi voluptatem\",\"slug\":\"modi-voluptatem\",\"icon\":null,\"status\":{\"value\":1,\"label\":\"active\"},\"real_depth\":0,\"created_at\":\"2022-02-08T15:36:06.000000Z\",\"created_at_diff\":\"1 second ago\",\"updated_at\":\"2022-02-08T15:36:06.000000Z\",\"updated_at_diff\":\"1 second ago\"}],\"meta\":\"Paging, filtering and sorting information\"}",
                            "name": ""
                        }
                    ]
                },
                {
                    "name": "Index of post's categories",
                    "request": {
                        "url": {
                            "host": "{{baseUrl}}",
                            "path": "api\/categories\/post\/index",
                            "query": [],
                            "raw": "{{baseUrl}}\/api\/categories\/post\/index"
                        },
                        "method": "POST",
                        "header": [
                            {
                                "key": "Content-Type",
                                "value": "application\/json"
                            },
                            {
                                "key": "Accept",
                                "value": "application\/json"
                            }
                        ],
                        "body": {
                            "mode": "raw",
                            "raw": "{\"page\":1,\"filter\":{\"except\":[7],\"search\":\"\",\"status\":1,\"parent\":0,\"orderby\":\"\",\"paginate\":25}}"
                        },
                        "description": "",
                        "auth": {
                            "type": "noauth"
                        }
                    },
                    "response": [
                        {
                            "header": [],
                            "code": 200,
                            "body": "{\"data\":[{\"id\":2573,\"name\":\"necessitatibus ipsum\",\"slug\":\"necessitatibus-ipsum\",\"icon\":null,\"status\":{\"value\":1,\"label\":\"active\"},\"real_depth\":0,\"created_at\":\"2022-02-08T15:36:08.000000Z\",\"created_at_diff\":\"1 second ago\",\"updated_at\":\"2022-02-08T15:36:08.000000Z\",\"updated_at_diff\":\"1 second ago\"},{\"id\":2574,\"name\":\"quasi rerum\",\"slug\":\"quasi-rerum\",\"icon\":null,\"status\":{\"value\":1,\"label\":\"active\"},\"real_depth\":0,\"created_at\":\"2022-02-08T15:36:08.000000Z\",\"created_at_diff\":\"1 second ago\",\"updated_at\":\"2022-02-08T15:36:08.000000Z\",\"updated_at_diff\":\"1 second ago\"}],\"meta\":\"Paging, filtering and sorting information\"}",
                            "name": ""
                        }
                    ]
                },
                {
                    "name": "Index of categories",
                    "request": {
                        "url": {
                            "host": "{{baseUrl}}",
                            "path": "api\/categories\/index",
                            "query": [],
                            "raw": "{{baseUrl}}\/api\/categories\/index"
                        },
                        "method": "POST",
                        "header": [
                            {
                                "key": "Content-Type",
                                "value": "application\/json"
                            },
                            {
                                "key": "Accept",
                                "value": "application\/json"
                            }
                        ],
                        "body": {
                            "mode": "raw",
                            "raw": "{\"page\":1,\"filter\":{\"except\":[19],\"search\":\"\",\"status\":1,\"parent\":0,\"orderby\":\"\",\"paginate\":25}}"
                        },
                        "description": "",
                        "auth": {
                            "type": "noauth"
                        }
                    },
                    "response": [
                        {
                            "header": [],
                            "code": 200,
                            "body": "{\"data\":[{\"id\":12,\"name\":\"Gabinety kosmetyczne\",\"slug\":\"gabinety-kosmetyczne\",\"icon\":null,\"status\":{\"value\":1,\"label\":\"active\"},\"real_depth\":1,\"created_at\":\"2009-08-21T08:36:46.000000Z\",\"created_at_diff\":\"12 years 5 months ago\",\"updated_at\":\"2009-08-21T08:36:46.000000Z\",\"updated_at_diff\":\"12 years 5 months ago\"},{\"id\":12,\"name\":\"Gabinety kosmetyczne\",\"slug\":\"gabinety-kosmetyczne\",\"icon\":null,\"status\":{\"value\":1,\"label\":\"active\"},\"real_depth\":1,\"created_at\":\"2009-08-21T08:36:46.000000Z\",\"created_at_diff\":\"12 years 5 months ago\",\"updated_at\":\"2009-08-21T08:36:46.000000Z\",\"updated_at_diff\":\"12 years 5 months ago\"}],\"meta\":\"Paging, filtering and sorting information\"}",
                            "name": ""
                        }
                    ]
                }
            ]
        },
        {
            "name": "Endpoints",
            "description": "",
            "item": [
                {
                    "name": "api\/dirs\/{dir}",
                    "request": {
                        "url": {
                            "host": "{{baseUrl}}",
                            "path": "api\/dirs\/:dir",
                            "query": [],
                            "raw": "{{baseUrl}}\/api\/dirs\/:dir",
                            "variable": [
                                {
                                    "id": "dir",
                                    "key": "dir",
                                    "value": "5",
                                    "description": ""
                                }
                            ]
                        },
                        "method": "PUT",
                        "header": [
                            {
                                "key": "Content-Type",
                                "value": "application\/json"
                            },
                            {
                                "key": "Accept",
                                "value": "application\/json"
                            }
                        ],
                        "body": null,
                        "description": "",
                        "auth": {
                            "type": "noauth"
                        }
                    },
                    "response": []
                },
                {
                    "name": "Undocumented function",
                    "request": {
                        "url": {
                            "host": "{{baseUrl}}",
                            "path": "api\/payments\/dir\/verify\/:driver",
                            "query": [],
                            "raw": "{{baseUrl}}\/api\/payments\/dir\/verify\/:driver",
                            "variable": [
                                {
                                    "id": "driver",
                                    "key": "driver",
                                    "value": "XeU3",
                                    "description": ""
                                }
                            ]
                        },
                        "method": "POST",
                        "header": [
                            {
                                "key": "Content-Type",
                                "value": "application\/json"
                            },
                            {
                                "key": "Accept",
                                "value": "application\/json"
                            }
                        ],
                        "body": null,
                        "description": "",
                        "auth": {
                            "type": "noauth"
                        }
                    },
                    "response": []
                },
                {
                    "name": "Undocumented function",
                    "request": {
                        "url": {
                            "host": "{{baseUrl}}",
                            "path": "api\/thumbnails\/reload",
                            "query": [],
                            "raw": "{{baseUrl}}\/api\/thumbnails\/reload"
                        },
                        "method": "PATCH",
                        "header": [
                            {
                                "key": "Content-Type",
                                "value": "application\/json"
                            },
                            {
                                "key": "Accept",
                                "value": "application\/json"
                            }
                        ],
                        "body": {
                            "mode": "raw",
                            "raw": "{\"url\":\"http:\\\/\\\/mox.eailb\\\/\"}"
                        },
                        "description": "",
                        "auth": {
                            "type": "noauth"
                        }
                    },
                    "response": []
                }
            ]
        },
        {
            "name": "Posts",
            "description": "\n> Routes:\n\n    \/routes\/vendor\/icore\/api\/posts.php\n\n> Controller:\n\n    N1ebieski\\ICore\\Http\\Controllers\\Api\\Post\\PostController\n\n> Resource:\n\n    N1ebieski\\ICore\\Http\\Resources\\Post\\PostResource\n\nPermissions:\n\n- api.* - access to all api endpoints\n- api.posts.* - access to all posts endpoints\n- api.posts.view - access to endpoints with collection of posts",
            "item": [
                {
                    "name": "Index of posts",
                    "request": {
                        "url": {
                            "host": "{{baseUrl}}",
                            "path": "api\/posts\/index",
                            "query": [],
                            "raw": "{{baseUrl}}\/api\/posts\/index"
                        },
                        "method": "POST",
                        "header": [
                            {
                                "key": "Content-Type",
                                "value": "application\/json"
                            },
                            {
                                "key": "Accept",
                                "value": "application\/json"
                            }
                        ],
                        "body": {
                            "mode": "raw",
                            "raw": "{\"page\":1,\"filter\":{\"except\":[9],\"search\":\"\",\"status\":1,\"category\":1,\"orderby\":\"updated_at|desc\",\"paginate\":25}}"
                        },
                        "description": "<aside class=\"notice\">Available only to users with permission: api.posts.view.<\/aside>"
                    },
                    "response": [
                        {
                            "header": [],
                            "code": 200,
                            "body": "{\"data\":[{\"id\":209,\"slug\":\"explicabo-qui-voluptatibus-nihil-ipsam-et\",\"title\":\"Explicabo qui voluptatibus nihil ipsam et.\",\"short_content\":\"Quos deserunt in voluptas ut omnis. Ut blanditiis nihil dicta aperiam ut. Qui cumque sed ad. Laboriosam neque est dolorem est. Sit dolores nemo distinctio quae autem. Cupiditate excepturi consequuntur nam sapiente fugit et. Cumque explicabo ut aliquid ea delectus dicta. Ratione placeat expedita necessitatibus quae est incidunt. Est ipsam ab nemo sed ad et tenetur consequuntur. Eos sit asperiores eos facere. Dolorem adipisci omnis est aut aut expedita. Fuga autem expedita voluptatem qui. Corporis\",\"content\":\"Quos deserunt in voluptas ut omnis. Ut blanditiis nihil dicta aperiam ut. Qui cumque sed ad. Laboriosam neque est dolorem est. Sit dolores nemo distinctio quae autem. Cupiditate excepturi consequuntur nam sapiente fugit et. Cumque explicabo ut aliquid ea delectus dicta. Ratione placeat expedita necessitatibus quae est incidunt. Est ipsam ab nemo sed ad et tenetur consequuntur. Eos sit asperiores eos facere. Dolorem adipisci omnis est aut aut expedita. Fuga autem expedita voluptatem qui. Corporis quo et voluptatem porro tempore qui quo. Cum sapiente esse occaecati quod et. Accusantium iure maxime vel velit sapiente ex sapiente. Velit dolor officiis vel voluptatem culpa eligendi. Mollitia est reiciendis necessitatibus aspernatur nobis cumque. Beatae voluptatibus totam voluptatibus facilis. Necessitatibus ullam quibusdam libero. Magni corporis sint sint optio id voluptas. Explicabo optio unde suscipit ut. Omnis iure iure quasi deserunt tempore deleniti dolores. Provident qui voluptatibus rerum adipisci iusto et eum delectus. Ex saepe non vitae commodi libero pariatur quae. In non dolore qui in harum. Omnis tempora aut quibusdam. Sint veritatis cupiditate excepturi necessitatibus voluptas exercitationem quis. Assumenda nihil aut qui impedit quidem et. Velit corporis voluptatem repudiandae exercitationem soluta sed. Omnis eum quaerat veritatis sunt vel qui. Minus aut animi qui omnis. Eos aperiam iusto placeat quibusdam quam et ab. Ducimus ut voluptate dolorem eveniet suscipit sunt cumque vero. Quo quidem laboriosam vero sunt ut aperiam. Sint maxime est qui quia. Quisquam eos eveniet non qui. Sint delectus quaerat sed aperiam quo saepe. Nam quidem omnis nesciunt illum. Fuga nobis architecto sed veniam dolore nostrum. Dolorem aut quod beatae molestias quo sint reprehenderit. Libero eaque ut quia. Sit accusantium est eum est ut molestiae sed.\",\"content_html\":\"<p>Quos deserunt in voluptas ut omnis. Ut blanditiis nihil dicta aperiam ut. Qui cumque sed ad. Laboriosam neque est dolorem est. Sit dolores nemo distinctio quae autem. Cupiditate excepturi consequuntur nam sapiente fugit et. Cumque explicabo ut aliquid ea delectus dicta. Ratione placeat expedita necessitatibus quae est incidunt. Est ipsam ab nemo sed ad et tenetur consequuntur. Eos sit asperiores eos facere. Dolorem adipisci omnis est aut aut expedita. Fuga autem expedita voluptatem qui. Corporis quo et voluptatem porro tempore qui quo. Cum sapiente esse occaecati quod et. Accusantium iure maxime vel velit sapiente ex sapiente. Velit dolor officiis vel voluptatem culpa eligendi. Mollitia est reiciendis necessitatibus aspernatur nobis cumque. Beatae voluptatibus totam voluptatibus facilis. Necessitatibus ullam quibusdam libero. Magni corporis sint sint optio id voluptas. Explicabo optio unde suscipit ut. Omnis iure iure quasi deserunt tempore deleniti dolores. Provident qui voluptatibus rerum adipisci iusto et eum delectus. Ex saepe non vitae commodi libero pariatur quae. In non dolore qui in harum. Omnis tempora aut quibusdam. Sint veritatis cupiditate excepturi necessitatibus voluptas exercitationem quis. Assumenda nihil aut qui impedit quidem et. Velit corporis voluptatem repudiandae exercitationem soluta sed. Omnis eum quaerat veritatis sunt vel qui. Minus aut animi qui omnis. Eos aperiam iusto placeat quibusdam quam et ab. Ducimus ut voluptate dolorem eveniet suscipit sunt cumque vero. Quo quidem laboriosam vero sunt ut aperiam. Sint maxime est qui quia. Quisquam eos eveniet non qui. Sint delectus quaerat sed aperiam quo saepe. Nam quidem omnis nesciunt illum. Fuga nobis architecto sed veniam dolore nostrum. Dolorem aut quod beatae molestias quo sint reprehenderit. Libero eaque ut quia. Sit accusantium est eum est ut molestiae sed.<\\\/p>\",\"no_more_content_html\":\"<p>Quos deserunt in voluptas ut omnis. Ut blanditiis nihil dicta aperiam ut. Qui cumque sed ad. Laboriosam neque est dolorem est. Sit dolores nemo distinctio quae autem. Cupiditate excepturi consequuntur nam sapiente fugit et. Cumque explicabo ut aliquid ea delectus dicta. Ratione placeat expedita necessitatibus quae est incidunt. Est ipsam ab nemo sed ad et tenetur consequuntur. Eos sit asperiores eos facere. Dolorem adipisci omnis est aut aut expedita. Fuga autem expedita voluptatem qui. Corporis quo et voluptatem porro tempore qui quo. Cum sapiente esse occaecati quod et. Accusantium iure maxime vel velit sapiente ex sapiente. Velit dolor officiis vel voluptatem culpa eligendi. Mollitia est reiciendis necessitatibus aspernatur nobis cumque. Beatae voluptatibus totam voluptatibus facilis. Necessitatibus ullam quibusdam libero. Magni corporis sint sint optio id voluptas. Explicabo optio unde suscipit ut. Omnis iure iure quasi deserunt tempore deleniti dolores. Provident qui voluptatibus rerum adipisci iusto et eum delectus. Ex saepe non vitae commodi libero pariatur quae. In non dolore qui in harum. Omnis tempora aut quibusdam. Sint veritatis cupiditate excepturi necessitatibus voluptas exercitationem quis. Assumenda nihil aut qui impedit quidem et. Velit corporis voluptatem repudiandae exercitationem soluta sed. Omnis eum quaerat veritatis sunt vel qui. Minus aut animi qui omnis. Eos aperiam iusto placeat quibusdam quam et ab. Ducimus ut voluptate dolorem eveniet suscipit sunt cumque vero. Quo quidem laboriosam vero sunt ut aperiam. Sint maxime est qui quia. Quisquam eos eveniet non qui. Sint delectus quaerat sed aperiam quo saepe. Nam quidem omnis nesciunt illum. Fuga nobis architecto sed veniam dolore nostrum. Dolorem aut quod beatae molestias quo sint reprehenderit. Libero eaque ut quia. Sit accusantium est eum est ut molestiae sed.<\\\/p>\",\"less_content_html\":\"<p>Quos deserunt in voluptas ut omnis. Ut blanditiis nihil dicta aperiam ut. Qui cumque sed ad. Laboriosam neque est dolorem est. Sit dolores nemo distinctio quae autem. Cupiditate excepturi consequuntur nam sapiente fugit et. Cumque explicabo ut aliquid ea delectus dicta. Ratione placeat expedita necessitatibus quae est incidunt. Est ipsam ab nemo sed ad et tenetur consequuntur. Eos sit asperiores eos facere. Dolorem adipisci omnis est aut aut expedita. Fuga autem expedita voluptatem qui. Corporis quo et voluptatem porro tempore qui quo. Cum sapiente esse occaecati quod et. Accusantium iure maxime vel velit sapiente ex sapiente. Velit dolor officiis vel voluptatem culpa eligendi. Mollitia est reiciendis necessitatibus aspernatur nobis cumque. Beatae voluptatibus totam voluptatibus facilis. Necessitatibus ullam quibusdam libero. Magni corporis sint sint optio id voluptas. Explicabo optio unde suscipit ut. Omnis iure iure quasi deserunt tempore deleniti dolores. Provident qui voluptatibus rerum adipisci iusto et eum delectus. Ex saepe non vitae commodi libero pariatur quae. In non dolore qui in harum. Omnis tempora aut quibusdam. Sint veritatis cupiditate excepturi necessitatibus voluptas exercitationem quis. Assumenda nihil aut qui impedit quidem et. Velit corporis voluptatem repudiandae exercitationem soluta sed. Omnis eum quaerat veritatis sunt vel qui. Minus aut animi qui omnis. Eos aperiam iusto placeat quibusdam quam et ab. Ducimus ut voluptate dolorem eveniet suscipit sunt cumque vero. Quo quidem laboriosam vero sunt ut aperiam. Sint maxime est qui quia. Quisquam eos eveniet non qui. Sint delectus quaerat sed aperiam quo saepe. Nam quidem omnis nesciunt illum. Fuga nobis architecto sed veniam dolore nostrum. Dolorem aut quod beatae molestias quo sint reprehenderit. Libero eaque ut quia. Sit accusantium est eum est ut molestiae sed.<\\\/p>\",\"seo_title\":null,\"meta_title\":\"Explicabo qui voluptatibus nihil ipsam et.\",\"seo_desc\":\"Officiis et perferendis et quia excepturi quod. Quia tempore dolores sit dolorem facere illum voluptatum.\",\"meta_desc\":\"Officiis et perferendis et quia excepturi quod. Quia tempore dolores sit dolorem facere illum voluptatum.\",\"seo_noindex\":true,\"seo_nofollow\":false,\"status\":{\"value\":1,\"label\":\"active\"},\"comment\":false,\"first_image\":null,\"published_at\":\"2022-02-06T19:09:03.000000Z\",\"published_at_diff\":\"1 day 20 hours ago\",\"created_at\":\"2022-02-08T15:36:07.000000Z\",\"created_at_diff\":\"1 second ago\",\"updated_at\":\"2022-02-08T15:36:07.000000Z\",\"updated_at_diff\":\"1 second ago\",\"links\":{\"web\":\"http:\\\/\\\/idir.test:8443\\\/posts\\\/explicabo-qui-voluptatibus-nihil-ipsam-et\",\"admin\":\"http:\\\/\\\/idir.test:8443\\\/admin\\\/posts\\\/index?filter%5Bsearch%5D=id%3A%22209%22\"},\"user\":{\"id\":12295,\"name\":\"Miss Rowena Schoen\",\"status\":{\"value\":0,\"label\":\"inactive\"},\"created_at\":\"2022-02-08T15:36:07.000000Z\",\"created_at_diff\":\"1 second ago\",\"updated_at\":\"2022-02-08T15:36:07.000000Z\",\"updated_at_diff\":\"1 second ago\"}},{\"id\":210,\"slug\":\"velit-quia-in-libero\",\"title\":\"Velit quia in libero.\",\"short_content\":\"Quo sequi incidunt sit nesciunt. Minima inventore esse aliquam voluptatem. Aut rerum vel occaecati est at asperiores. Aut dolorum tenetur voluptatem deserunt commodi iusto. Alias eius voluptatem et qui rem recusandae. Ea inventore ut numquam sed qui dolor. Quia voluptas qui unde est eveniet. Corporis quo earum aut. Optio eum perspiciatis aut autem earum. Molestiae nobis earum quam iure. Inventore eaque nobis dolore dolorem. Sed ratione aliquam nam dolor debitis. Recusandae ipsam nostrum veniam s\",\"content\":\"Quo sequi incidunt sit nesciunt. Minima inventore esse aliquam voluptatem. Aut rerum vel occaecati est at asperiores. Aut dolorum tenetur voluptatem deserunt commodi iusto. Alias eius voluptatem et qui rem recusandae. Ea inventore ut numquam sed qui dolor. Quia voluptas qui unde est eveniet. Corporis quo earum aut. Optio eum perspiciatis aut autem earum. Molestiae nobis earum quam iure. Inventore eaque nobis dolore dolorem. Sed ratione aliquam nam dolor debitis. Recusandae ipsam nostrum veniam sit ratione repudiandae et. Voluptas voluptatum veniam eligendi sunt iste voluptatem. Nihil voluptatibus et maiores tenetur rerum. Aperiam et cupiditate rem omnis vero repudiandae. Fugiat excepturi illum tempore eum sed. Aliquam est illo est non quae sapiente. Minus sed ratione aut eaque quisquam consequuntur id illum. Dicta ipsa repudiandae harum officia consequatur velit qui. Possimus consequatur aliquid rem dolores doloremque repellendus. Eos nihil saepe dolor. Sit vel pariatur dignissimos nesciunt itaque. Aliquid ut reprehenderit magnam voluptas officiis. Et eius cumque possimus quia minus molestiae. Vel voluptas culpa cupiditate ipsam incidunt velit magni. Aut est voluptatem minima autem modi velit. Tenetur vero velit ipsam autem at. Aut ut dolores quam corrupti officiis voluptatum tempora. Atque totam at sint placeat incidunt. Velit voluptas vel deserunt illo commodi officia quidem. Doloribus nesciunt maxime nobis totam nesciunt. Architecto pariatur alias nesciunt mollitia. Quis sunt possimus modi repellat eos. Eum at et id dolor commodi et laboriosam. Sed quod eveniet rerum vel omnis ut natus. Illum necessitatibus veritatis rerum quos sapiente. Saepe nisi dolorem neque eius ut. Officia repudiandae facilis saepe aut. Ut ratione amet pariatur et amet. Eveniet doloribus quas tempora et ut temporibus. Et fuga itaque id quis a et.\",\"content_html\":\"<p>Quo sequi incidunt sit nesciunt. Minima inventore esse aliquam voluptatem. Aut rerum vel occaecati est at asperiores. Aut dolorum tenetur voluptatem deserunt commodi iusto. Alias eius voluptatem et qui rem recusandae. Ea inventore ut numquam sed qui dolor. Quia voluptas qui unde est eveniet. Corporis quo earum aut. Optio eum perspiciatis aut autem earum. Molestiae nobis earum quam iure. Inventore eaque nobis dolore dolorem. Sed ratione aliquam nam dolor debitis. Recusandae ipsam nostrum veniam sit ratione repudiandae et. Voluptas voluptatum veniam eligendi sunt iste voluptatem. Nihil voluptatibus et maiores tenetur rerum. Aperiam et cupiditate rem omnis vero repudiandae. Fugiat excepturi illum tempore eum sed. Aliquam est illo est non quae sapiente. Minus sed ratione aut eaque quisquam consequuntur id illum. Dicta ipsa repudiandae harum officia consequatur velit qui. Possimus consequatur aliquid rem dolores doloremque repellendus. Eos nihil saepe dolor. Sit vel pariatur dignissimos nesciunt itaque. Aliquid ut reprehenderit magnam voluptas officiis. Et eius cumque possimus quia minus molestiae. Vel voluptas culpa cupiditate ipsam incidunt velit magni. Aut est voluptatem minima autem modi velit. Tenetur vero velit ipsam autem at. Aut ut dolores quam corrupti officiis voluptatum tempora. Atque totam at sint placeat incidunt. Velit voluptas vel deserunt illo commodi officia quidem. Doloribus nesciunt maxime nobis totam nesciunt. Architecto pariatur alias nesciunt mollitia. Quis sunt possimus modi repellat eos. Eum at et id dolor commodi et laboriosam. Sed quod eveniet rerum vel omnis ut natus. Illum necessitatibus veritatis rerum quos sapiente. Saepe nisi dolorem neque eius ut. Officia repudiandae facilis saepe aut. Ut ratione amet pariatur et amet. Eveniet doloribus quas tempora et ut temporibus. Et fuga itaque id quis a et.<\\\/p>\",\"no_more_content_html\":\"<p>Quo sequi incidunt sit nesciunt. Minima inventore esse aliquam voluptatem. Aut rerum vel occaecati est at asperiores. Aut dolorum tenetur voluptatem deserunt commodi iusto. Alias eius voluptatem et qui rem recusandae. Ea inventore ut numquam sed qui dolor. Quia voluptas qui unde est eveniet. Corporis quo earum aut. Optio eum perspiciatis aut autem earum. Molestiae nobis earum quam iure. Inventore eaque nobis dolore dolorem. Sed ratione aliquam nam dolor debitis. Recusandae ipsam nostrum veniam sit ratione repudiandae et. Voluptas voluptatum veniam eligendi sunt iste voluptatem. Nihil voluptatibus et maiores tenetur rerum. Aperiam et cupiditate rem omnis vero repudiandae. Fugiat excepturi illum tempore eum sed. Aliquam est illo est non quae sapiente. Minus sed ratione aut eaque quisquam consequuntur id illum. Dicta ipsa repudiandae harum officia consequatur velit qui. Possimus consequatur aliquid rem dolores doloremque repellendus. Eos nihil saepe dolor. Sit vel pariatur dignissimos nesciunt itaque. Aliquid ut reprehenderit magnam voluptas officiis. Et eius cumque possimus quia minus molestiae. Vel voluptas culpa cupiditate ipsam incidunt velit magni. Aut est voluptatem minima autem modi velit. Tenetur vero velit ipsam autem at. Aut ut dolores quam corrupti officiis voluptatum tempora. Atque totam at sint placeat incidunt. Velit voluptas vel deserunt illo commodi officia quidem. Doloribus nesciunt maxime nobis totam nesciunt. Architecto pariatur alias nesciunt mollitia. Quis sunt possimus modi repellat eos. Eum at et id dolor commodi et laboriosam. Sed quod eveniet rerum vel omnis ut natus. Illum necessitatibus veritatis rerum quos sapiente. Saepe nisi dolorem neque eius ut. Officia repudiandae facilis saepe aut. Ut ratione amet pariatur et amet. Eveniet doloribus quas tempora et ut temporibus. Et fuga itaque id quis a et.<\\\/p>\",\"less_content_html\":\"<p>Quo sequi incidunt sit nesciunt. Minima inventore esse aliquam voluptatem. Aut rerum vel occaecati est at asperiores. Aut dolorum tenetur voluptatem deserunt commodi iusto. Alias eius voluptatem et qui rem recusandae. Ea inventore ut numquam sed qui dolor. Quia voluptas qui unde est eveniet. Corporis quo earum aut. Optio eum perspiciatis aut autem earum. Molestiae nobis earum quam iure. Inventore eaque nobis dolore dolorem. Sed ratione aliquam nam dolor debitis. Recusandae ipsam nostrum veniam sit ratione repudiandae et. Voluptas voluptatum veniam eligendi sunt iste voluptatem. Nihil voluptatibus et maiores tenetur rerum. Aperiam et cupiditate rem omnis vero repudiandae. Fugiat excepturi illum tempore eum sed. Aliquam est illo est non quae sapiente. Minus sed ratione aut eaque quisquam consequuntur id illum. Dicta ipsa repudiandae harum officia consequatur velit qui. Possimus consequatur aliquid rem dolores doloremque repellendus. Eos nihil saepe dolor. Sit vel pariatur dignissimos nesciunt itaque. Aliquid ut reprehenderit magnam voluptas officiis. Et eius cumque possimus quia minus molestiae. Vel voluptas culpa cupiditate ipsam incidunt velit magni. Aut est voluptatem minima autem modi velit. Tenetur vero velit ipsam autem at. Aut ut dolores quam corrupti officiis voluptatum tempora. Atque totam at sint placeat incidunt. Velit voluptas vel deserunt illo commodi officia quidem. Doloribus nesciunt maxime nobis totam nesciunt. Architecto pariatur alias nesciunt mollitia. Quis sunt possimus modi repellat eos. Eum at et id dolor commodi et laboriosam. Sed quod eveniet rerum vel omnis ut natus. Illum necessitatibus veritatis rerum quos sapiente. Saepe nisi dolorem neque eius ut. Officia repudiandae facilis saepe aut. Ut ratione amet pariatur et amet. Eveniet doloribus quas tempora et ut temporibus. Et fuga itaque id quis a et.<\\\/p>\",\"seo_title\":null,\"meta_title\":\"Velit quia in libero.\",\"seo_desc\":\"Dolores voluptatem itaque nesciunt sit beatae et non. Voluptates occaecati fugiat qui eum dolores sunt et placeat. Harum culpa veritatis et corporis blanditiis.\",\"meta_desc\":\"Dolores voluptatem itaque nesciunt sit beatae et non. Voluptates occaecati fugiat qui eum dolores sunt et placeat. Harum culpa veritatis et corporis blanditiis.\",\"seo_noindex\":true,\"seo_nofollow\":false,\"status\":{\"value\":1,\"label\":\"active\"},\"comment\":true,\"first_image\":null,\"published_at\":\"2021-04-23T01:21:06.000000Z\",\"published_at_diff\":\"9 months 2 weeks ago\",\"created_at\":\"2022-02-08T15:36:07.000000Z\",\"created_at_diff\":\"1 second ago\",\"updated_at\":\"2022-02-08T15:36:07.000000Z\",\"updated_at_diff\":\"1 second ago\",\"links\":{\"web\":\"http:\\\/\\\/idir.test:8443\\\/posts\\\/velit-quia-in-libero\",\"admin\":\"http:\\\/\\\/idir.test:8443\\\/admin\\\/posts\\\/index?filter%5Bsearch%5D=id%3A%22210%22\"},\"user\":{\"id\":12296,\"name\":\"Frederik Marvin\",\"status\":{\"value\":0,\"label\":\"inactive\"},\"created_at\":\"2022-02-08T15:36:07.000000Z\",\"created_at_diff\":\"1 second ago\",\"updated_at\":\"2022-02-08T15:36:07.000000Z\",\"updated_at_diff\":\"1 second ago\"}}],\"meta\":\"Paging, filtering and sorting information\"}",
                            "name": ""
                        }
                    ]
                }
            ]
        },
        {
            "name": "Tags",
            "description": "\n> Routes:\n\n    \/routes\/vendor\/icore\/api\/tags.php\n\n> Controller:\n\n    N1ebieski\\ICore\\Http\\Controllers\\Api\\Tag\\TagController\n\n> Resource:\n\n    N1ebieski\\ICore\\Http\\Resources\\Tag\\TagResource\n\nPermissions:\n\n- api.* - access to all api endpoints\n- api.tags.* - access to all tags endpoints\n- api.tags.view - access to endpoints with collection of tags",
            "item": [
                {
                    "name": "Index of tags",
                    "request": {
                        "url": {
                            "host": "{{baseUrl}}",
                            "path": "api\/tags\/index",
                            "query": [],
                            "raw": "{{baseUrl}}\/api\/tags\/index"
                        },
                        "method": "POST",
                        "header": [
                            {
                                "key": "Content-Type",
                                "value": "application\/json"
                            },
                            {
                                "key": "Accept",
                                "value": "application\/json"
                            }
                        ],
                        "body": {
                            "mode": "raw",
                            "raw": "{\"page\":1,\"filter\":{\"except\":[9],\"search\":\"\",\"orderby\":\"updated_at|asc\",\"paginate\":25}}"
                        },
                        "description": "",
                        "auth": {
                            "type": "noauth"
                        }
                    },
                    "response": [
                        {
                            "header": [],
                            "code": 200,
                            "body": "{\"data\":[{\"id\":1,\"name\":\"us\\u0142ugi galwaniczne\",\"slug\":\"uslugi-galwaniczne\",\"created_at\":\"2021-01-06T17:01:54.000000Z\",\"created_at_diff\":\"1 year 1 month ago\",\"updated_at\":\"2021-01-06T17:01:54.000000Z\",\"updated_at_diff\":\"1 year 1 month ago\"},{\"id\":1,\"name\":\"us\\u0142ugi galwaniczne\",\"slug\":\"uslugi-galwaniczne\",\"created_at\":\"2021-01-06T17:01:54.000000Z\",\"created_at_diff\":\"1 year 1 month ago\",\"updated_at\":\"2021-01-06T17:01:54.000000Z\",\"updated_at_diff\":\"1 year 1 month ago\"}],\"meta\":\"Paging, filtering and sorting information\"}",
                            "name": ""
                        }
                    ]
                }
            ]
        },
        {
            "name": "Users",
            "description": "\n> Routes:\n\n    \/routes\/vendor\/icore\/api\/users.php\n\n> Controller:\n\n    N1ebieski\\ICore\\Http\\Controllers\\Api\\User\\UserController\n\n> Resource:\n\n    N1ebieski\\ICore\\Http\\Resources\\User\\UserResource\n\nPermissions:\n\n- api.* - access to all api endpoints\n- api.users.* - access to all users endpoints\n- api.users.view - access to endpoints with collection of users",
            "item": [
                {
                    "name": "Index of users",
                    "request": {
                        "url": {
                            "host": "{{baseUrl}}",
                            "path": "api\/users\/index",
                            "query": [],
                            "raw": "{{baseUrl}}\/api\/users\/index"
                        },
                        "method": "POST",
                        "header": [
                            {
                                "key": "Content-Type",
                                "value": "application\/json"
                            },
                            {
                                "key": "Accept",
                                "value": "application\/json"
                            }
                        ],
                        "body": {
                            "mode": "raw",
                            "raw": "{\"page\":1,\"filter\":{\"except\":[18],\"search\":\"\",\"status\":1,\"role\":1,\"orderby\":\"created_at|asc\",\"paginate\":50}}"
                        },
                        "description": "<aside class=\"notice\">Available only to users with permissions: api.users.view and admin.users.view.<\/aside>"
                    },
                    "response": [
                        {
                            "header": [],
                            "code": 200,
                            "body": "{\"data\":[{\"id\":12292,\"name\":\"Mrs. Eleanora Mante\",\"status\":{\"value\":1,\"label\":\"active\"},\"created_at\":\"2022-02-08T15:36:06.000000Z\",\"created_at_diff\":\"1 second ago\",\"updated_at\":\"2022-02-08T15:36:06.000000Z\",\"updated_at_diff\":\"1 second ago\",\"roles\":[{\"id\":3,\"name\":\"user\",\"created_at\":\"2021-01-06T16:58:51.000000Z\",\"created_at_diff\":\"1 year 1 month ago\"}]},{\"id\":12293,\"name\":\"Lucas Stamm\",\"status\":{\"value\":1,\"label\":\"active\"},\"created_at\":\"2022-02-08T15:36:06.000000Z\",\"created_at_diff\":\"1 second ago\",\"updated_at\":\"2022-02-08T15:36:06.000000Z\",\"updated_at_diff\":\"1 second ago\",\"roles\":[{\"id\":3,\"name\":\"user\",\"created_at\":\"2021-01-06T16:58:51.000000Z\",\"created_at_diff\":\"1 year 1 month ago\"}]}],\"meta\":\"Paging, filtering and sorting information\"}",
                            "name": ""
                        }
                    ]
                }
            ]
        }
    ],
    "auth": {
        "type": "bearer"
    }
}